<?xml version="1.0" encoding="UTF-8"?><results version="2">    <cppcheck version="1.76.1"/>    <errors>        <error id="unreadVariable" severity="style" msg="Variable &apos;custom_action_num_calls&apos; is assigned a value that is never used." verbose="Variable &apos;custom_action_num_calls&apos; is assigned a value that is never used." cwe="563">            <location file0="D:\New folder (2)\PowerToys-1\src\modules\windowwalker\dll\dllmain.cpp" file="D:\New folder (2)\PowerToys-1\src\modules\windowwalker\dll\dllmain.cpp" line="104"/>        </error>        <error id="unreadVariable" severity="style" msg="Variable &apos;event&apos; is assigned a value that is never used." verbose="Variable &apos;event&apos; is assigned a value that is never used." cwe="563">            <location file0="D:\New folder (2)\PowerToys-1\src\modules\windowwalker\dll\dllmain.cpp" file="D:\New folder (2)\PowerToys-1\src\modules\windowwalker\dll\dllmain.cpp" line="172"/>        </error>        <error id="unreadVariable" severity="style" msg="Variable &apos;event&apos; is assigned a value that is never used." verbose="Variable &apos;event&apos; is assigned a value that is never used." cwe="563">            <location file0="D:\New folder (2)\PowerToys-1\src\modules\windowwalker\dll\dllmain.cpp" file="D:\New folder (2)\PowerToys-1\src\modules\windowwalker\dll\dllmain.cpp" line="179"/>        </error>        <error id="unusedFunction" severity="style" msg="The function &apos;DllMain&apos; is never used." verbose="The function &apos;DllMain&apos; is never used." cwe="561">            <location file="D:\New folder (2)\PowerToys-1\src\modules\windowwalker\dll\dllmain.cpp" line="11"/>        </error>        <error id="unusedFunction" severity="style" msg="The function &apos;call_custom_action&apos; is never used." verbose="The function &apos;call_custom_action&apos; is never used." cwe="561">            <location file="D:\New folder (2)\PowerToys-1\src\modules\windowwalker\dll\dllmain.cpp" line="102"/>        </error>        <error id="unusedFunction" severity="style" msg="The function &apos;destroy&apos; is never used." verbose="The function &apos;destroy&apos; is never used." cwe="561">            <location file="D:\New folder (2)\PowerToys-1\src\modules\windowwalker\dll\dllmain.cpp" line="59"/>        </error>        <error id="unusedFunction" severity="style" msg="The function &apos;disable&apos; is never used." verbose="The function &apos;disable&apos; is never used." cwe="561">            <location file="D:\New folder (2)\PowerToys-1\src\modules\windowwalker\dll\dllmain.cpp" line="150"/>        </error>        <error id="unusedFunction" severity="style" msg="The function &apos;enable&apos; is never used." verbose="The function &apos;enable&apos; is never used." cwe="561">            <location file="D:\New folder (2)\PowerToys-1\src\modules\windowwalker\dll\dllmain.cpp" line="135"/>        </error>        <error id="unusedFunction" severity="style" msg="The function &apos;get_config&apos; is never used." verbose="The function &apos;get_config&apos; is never used." cwe="561">            <location file="D:\New folder (2)\PowerToys-1\src\modules\windowwalker\dll\dllmain.cpp" line="86"/>        </error>        <error id="unusedFunction" severity="style" msg="The function &apos;get_events&apos; is never used." verbose="The function &apos;get_events&apos; is never used." cwe="561">            <location file="D:\New folder (2)\PowerToys-1\src\modules\windowwalker\dll\dllmain.cpp" line="78"/>        </error>        <error id="unusedFunction" severity="style" msg="The function &apos;is_enabled&apos; is never used." verbose="The function &apos;is_enabled&apos; is never used." cwe="561">            <location file="D:\New folder (2)\PowerToys-1\src\modules\windowwalker\dll\dllmain.cpp" line="162"/>        </error>        <error id="unusedFunction" severity="style" msg="The function &apos;powertoy_create&apos; is never used." verbose="The function &apos;powertoy_create&apos; is never used." cwe="561">            <location file="D:\New folder (2)\PowerToys-1\src\modules\windowwalker\dll\dllmain.cpp" line="211"/>        </error>        <error id="unusedFunction" severity="style" msg="The function &apos;register_system_menu_helper&apos; is never used." verbose="The function &apos;register_system_menu_helper&apos; is never used." cwe="561">            <location file="D:\New folder (2)\PowerToys-1\src\modules\windowwalker\dll\dllmain.cpp" line="187"/>        </error>        <error id="unusedFunction" severity="style" msg="The function &apos;set_config&apos; is never used." verbose="The function &apos;set_config&apos; is never used." cwe="561">            <location file="D:\New folder (2)\PowerToys-1\src\modules\windowwalker\dll\dllmain.cpp" line="118"/>        </error>        <error id="unusedFunction" severity="style" msg="The function &apos;signal_event&apos; is never used." verbose="The function &apos;signal_event&apos; is never used." cwe="561">            <location file="D:\New folder (2)\PowerToys-1\src\modules\windowwalker\dll\dllmain.cpp" line="168"/>        </error>        <error id="unusedFunction" severity="style" msg="The function &apos;signal_system_menu_action&apos; is never used." verbose="The function &apos;signal_system_menu_action&apos; is never used." cwe="561">            <location file="D:\New folder (2)\PowerToys-1\src\modules\windowwalker\dll\dllmain.cpp" line="191"/>        </error>        <error id="unmatchedSuppression" severity="information" msg="Unmatched suppression: preprocessorErrorDirective" verbose="Unmatched suppression: preprocessorErrorDirective">            <location file="*" line="0"/>        </error>    </errors></results>